LICENSE.MIT
MANIFEST.in
README
README.rst
setup.cfg
setup.py
src/alphabetic/__init__.py
src/alphabetic/models.py
src/alphabetic/tags.py
src/alphabetic/urls.py
src/alphabetic/utils.py
src/alphabetic/views.py
src/alphabetic/templates/alphabetic/fragment.html
src/alphabetic_simple.egg-info/PKG-INFO
src/alphabetic_simple.egg-info/SOURCES.txt
src/alphabetic_simple.egg-info/dependency_links.txt
src/alphabetic_simple.egg-info/not-zip-safe
src/alphabetic_simple.egg-info/requires.txt
src/alphabetic_simple.egg-info/top_level.txt