Metadata-Version: 1.1
Name: alphabetic-simple
Version: 0.2
Summary: Alphabetic template tag to filter django queryset
Home-page: http://github.com/Arpaso/alphabetic-simple
Author: Arpaso
Author-email: arvid@arpaso.com
License: UNKNOWN
Download-URL: http://github.com/Arpaso/alphabetic-simple/tarball/0.2
Platform: UNKNOWN
Classifier: Development Status :: 4 - Beta
Classifier: Framework :: Django
Classifier: Intended Audience :: Developers
Classifier: Intended Audience :: System Administrators
Classifier: Operating System :: OS Independent
Classifier: Topic :: Software Development
